MANIFEST.in
README.rst
bootstrap-buildout.py
buildout.cfg
setup.cfg
setup.py
version.txt
antispoofing/__init__.py
antispoofing.evaluation.egg-info/PKG-INFO
antispoofing.evaluation.egg-info/SOURCES.txt
antispoofing.evaluation.egg-info/dependency_links.txt
antispoofing.evaluation.egg-info/entry_points.txt
antispoofing.evaluation.egg-info/requires.txt
antispoofing.evaluation.egg-info/top_level.txt
antispoofing/evaluation/__init__.py
antispoofing/evaluation/script/__init__.py
antispoofing/evaluation/script/calc_aue_value.py
antispoofing/evaluation/script/cmp_systems_epsc.py
antispoofing/evaluation/script/epsc_animation.py
antispoofing/evaluation/script/epsc_vs_non_epsc.py
antispoofing/evaluation/script/plot_countermeasures_comparison.py
antispoofing/evaluation/script/plot_epsc_on_demand.py
antispoofing/evaluation/script/plot_faceverif_comparison.py
antispoofing/evaluation/script/plot_fusionmethods_comparison.py
antispoofing/evaluation/script/plot_on_demand.py
antispoofing/evaluation/script/score_distr_generator.py
antispoofing/evaluation/utils/__init__.py
antispoofing/evaluation/utils/error_utils.py
doc/conf.py
doc/index.rst
doc/reference.rst
doc/userguide.rst