Metadata-Version: 1.0
Name: antispoofing.evaluation
Version: 2.0.5
Summary: Evaluation tools for verification systems under spoofing attacks: examples in face verification
Home-page: http://github.com/bioidiap/antispoofing.evaluation
Author: Ivana Chingovska
Author-email: Ivana Chingovska <ivana.chingovska@idiap.ch>
License: LICENSE.txt
Platform: UNKNOWN
